<?xml version="1.0" encoding="utf-8"?>
<TextureAtlas imagePath="end1.png">
	<!-- Created with Adobe Animate version 20.5.1.31044 -->
	<!-- http://www.adobe.com/products/animate.html -->
	<SubTexture name="end0000" x="1" y="1" width="1284" height="719"/>
	<SubTexture name="end0001" x="1289" y="1" width="1284" height="719"/>
	<SubTexture name="end0002" x="2577" y="1" width="1284" height="719"/>
	<SubTexture name="end0003" x="3865" y="1" width="1284" height="719"/>
	<SubTexture name="end0004" x="5153" y="1" width="1284" height="719"/>
	<SubTexture name="end0005" x="6441" y="1" width="1284" height="719"/>
	<SubTexture name="end0006" x="1" y="724" width="1284" height="719"/>
	<SubTexture name="end0007" x="1289" y="724" width="1284" height="719"/>
	<SubTexture name="end0008" x="2577" y="724" width="1284" height="719"/>
	<SubTexture name="end0009" x="3865" y="724" width="1284" height="719"/>
	<SubTexture name="end0010" x="5153" y="724" width="1284" height="719"/>
	<SubTexture name="end0011" x="6441" y="724" width="1284" height="719"/>
	<SubTexture name="end0012" x="1" y="1447" width="1284" height="719"/>
	<SubTexture name="end0013" x="1289" y="1447" width="1284" height="719"/>
	<SubTexture name="end0014" x="2577" y="1447" width="1284" height="719"/>
	<SubTexture name="end0015" x="3865" y="1447" width="1284" height="719"/>
	<SubTexture name="end0016" x="5153" y="1447" width="1284" height="719"/>
	<SubTexture name="end0017" x="6441" y="1447" width="1284" height="719"/>
	<SubTexture name="end0018" x="1" y="2170" width="1284" height="719"/>
	<SubTexture name="end0019" x="1289" y="2170" width="1284" height="719"/>
	<SubTexture name="end0020" x="2577" y="2170" width="1284" height="719"/>
	<SubTexture name="end0021" x="3865" y="2170" width="1284" height="719"/>
	<SubTexture name="end0022" x="5153" y="2170" width="1284" height="719"/>
	<SubTexture name="end0023" x="6441" y="2170" width="1284" height="719"/>
	<SubTexture name="end0024" x="1" y="2893" width="1284" height="719"/>
	<SubTexture name="end0025" x="1289" y="2893" width="1284" height="719"/>
	<SubTexture name="end0026" x="2577" y="2893" width="1284" height="719"/>
	<SubTexture name="end0027" x="3865" y="2893" width="1284" height="719"/>
	<SubTexture name="end0028" x="5153" y="2893" width="1284" height="719"/>
	<SubTexture name="end0029" x="6441" y="2893" width="1284" height="719"/>
	<SubTexture name="end0030" x="1289" y="1" width="1284" height="719"/>
	<SubTexture name="end0031" x="1" y="3616" width="1284" height="719"/>
	<SubTexture name="end0032" x="1289" y="3616" width="1284" height="719"/>
	<SubTexture name="end0033" x="2577" y="3616" width="1284" height="719"/>
	<SubTexture name="end0034" x="3865" y="3616" width="1284" height="719"/>
	<SubTexture name="end0035" x="5153" y="3616" width="1284" height="719"/>
	<SubTexture name="end0036" x="6441" y="3616" width="1284" height="719"/>
	<SubTexture name="end0037" x="1" y="4339" width="1284" height="719"/>
	<SubTexture name="end0038" x="1289" y="4339" width="1284" height="719"/>
	<SubTexture name="end0039" x="2577" y="4339" width="1284" height="719"/>
	<SubTexture name="end0040" x="3865" y="4339" width="1284" height="719"/>
	<SubTexture name="end0041" x="5153" y="4339" width="1284" height="719"/>
	<SubTexture name="end0042" x="6441" y="4339" width="1284" height="719"/>
	<SubTexture name="end0043" x="1" y="5062" width="1284" height="719"/>
	<SubTexture name="end0044" x="1289" y="5062" width="1284" height="719"/>
	<SubTexture name="end0045" x="2577" y="5062" width="1284" height="719"/>
	<SubTexture name="end0046" x="3865" y="5062" width="1284" height="719"/>
	<SubTexture name="end0047" x="2577" y="1447" width="1284" height="719"/>
	<SubTexture name="end0048" x="3865" y="1447" width="1284" height="719"/>
	<SubTexture name="end0049" x="5153" y="1447" width="1284" height="719"/>
	<SubTexture name="end0050" x="6441" y="1447" width="1284" height="719"/>
	<SubTexture name="end0051" x="1" y="2170" width="1284" height="719"/>
	<SubTexture name="end0052" x="1289" y="2170" width="1284" height="719"/>
	<SubTexture name="end0053" x="2577" y="2170" width="1284" height="719"/>
	<SubTexture name="end0054" x="3865" y="2170" width="1284" height="719"/>
	<SubTexture name="end0055" x="5153" y="2170" width="1284" height="719"/>
	<SubTexture name="end0056" x="6441" y="2170" width="1284" height="719"/>
	<SubTexture name="end0057" x="1" y="2893" width="1284" height="719"/>
	<SubTexture name="end0058" x="1289" y="2893" width="1284" height="719"/>
	<SubTexture name="end0059" x="2577" y="2893" width="1284" height="719"/>
	<SubTexture name="end0060" x="3865" y="2893" width="1284" height="719"/>
	<SubTexture name="end0061" x="5153" y="2893" width="1284" height="719"/>
	<SubTexture name="end0062" x="6441" y="2893" width="1284" height="719"/>
	<SubTexture name="end0063" x="5153" y="5062" width="1284" height="719"/>
	<SubTexture name="end0064" x="6441" y="5062" width="1284" height="719"/>
</TextureAtlas>
